{"openapi":"3.0.3","info":{"title":"Goa API","version":"0.0.1"},"servers":[{"url":"http://localhost:80","description":"Default server for mktextr"}],"paths":{"/tasks":{"get":{"tags":["mktextr"],"summary":"GetTaskQueue mktextr","operationId":"mktextr#GetTaskQueue","responses":{"200":{"description":"OK response.","content":{"application/json":{"schema":{"$ref":"#/components/schemas/GetTaskQueueResponseBody"},"example":{"tasks":["Deserunt sit ducimus.","Et velit eos non optio molestiae nam."]}}}}}}},"/tasks/{taskId}/complete":{"patch":{"tags":["mktextr"],"summary":"completeTask mktextr","operationId":"mktextr#completeTask","parameters":[{"name":"taskId","in":"path","description":"ID of the task","required":true,"schema":{"type":"string","description":"ID of the task","example":"Est minima."},"example":"Ut impedit aut."}],"requestBody":{"required":true,"content":{"multipart/form-data":{"schema":{"$ref":"#/components/schemas/CompleteTaskRequestBody"},"example":{"extension":"Autem velit placeat et.","file":"VmVsaXQgZXQgcmVwdWRpYW5kYWUu"}}}},"responses":{"200":{"description":"OK response."}}}},"/textures":{"get":{"tags":["mktextr"],"summary":"getTextureByCoordinates mktextr","operationId":"mktextr#getTextureByCoordinates","parameters":[{"name":"worldId","in":"query","description":"WorldId","allowEmptyValue":true,"required":true,"schema":{"type":"string","description":"WorldId","example":"Debitis veniam deleniti."},"example":"Qui quis nobis dolores."},{"name":"x","in":"query","description":"Texture X","allowEmptyValue":true,"required":true,"schema":{"type":"integer","description":"Texture X","example":7117580923803438106,"format":"int64"},"example":683409081616245358},{"name":"y","in":"query","description":"Texture Y","allowEmptyValue":true,"required":true,"schema":{"type":"integer","description":"Texture Y","example":3599830644514005638,"format":"int64"},"example":5002806041006688025}],"responses":{"200":{"description":"OK response.","content":{"application/json":{"schema":{"$ref":"#/components/schemas/GetTextureByCoordinatesResponse"},"example":{"baseMapUrl":"Corporis nihil autem.","contourMapUrl":"Vero deserunt rem id molestiae quidem nihil.","sub_state":"Qui et.","texture_set_state":"Dolore voluptatem incidunt."}}}},"206":{"description":"Partial Content response.","content":{"application/json":{"schema":{"$ref":"#/components/schemas/GetTextureByCoordinatesResponse"},"example":{"baseMapUrl":"Temporibus voluptate vel voluptas velit.","contourMapUrl":"Possimus possimus aut.","sub_state":"Impedit recusandae reprehenderit et repellat qui.","texture_set_state":"Praesentium laborum corporis et."}}}},"400":{"description":"Bad Request response.","content":{"application/json":{"schema":{"$ref":"#/components/schemas/GetTextureByCoordinatesResponse"},"example":{"baseMapUrl":"Fugit nemo dolorem.","contourMapUrl":"Consequatur impedit voluptas adipisci consectetur voluptate quia.","sub_state":"Saepe iure repellendus perferendis quasi et.","texture_set_state":"Dicta maxime."}}}}}}}},"components":{"schemas":{"CompleteTaskRequestBody":{"type":"object","properties":{"extension":{"type":"string","description":"ID of the task","example":"Qui dolores possimus voluptas culpa ea."},"file":{"type":"string","description":"The file to upload","example":"TmloaWwgZXN0IGR1Y2ltdXMgaW4u","format":"binary"}},"example":{"extension":"Possimus omnis nostrum magni.","file":"Vm9sdXB0YXRlcyBhdXQu"},"required":["file","extension"]},"GetTaskQueueResponseBody":{"type":"object","properties":{"tasks":{"type":"array","items":{"type":"string","example":"Alias omnis et."},"example":["Suscipit veritatis aliquam deleniti aut in.","Pariatur sunt.","Quia assumenda natus."]}},"example":{"tasks":["Dolorum occaecati rerum accusamus sint.","Quibusdam delectus qui ut nihil.","Odio praesentium."]}},"GetTextureByCoordinatesResponse":{"type":"object","properties":{"baseMapUrl":{"type":"string","example":"Voluptatem tenetur eius optio consequatur."},"contourMapUrl":{"type":"string","example":"Quos at."},"sub_state":{"type":"string","example":"Esse veniam omnis tempora sint non."},"texture_set_state":{"type":"string","example":"Corporis beatae vero qui voluptatem."}},"description":"Texture set payload","example":{"baseMapUrl":"Voluptate reprehenderit assumenda unde eius dicta harum.","contourMapUrl":"Alias aspernatur fugiat sint.","sub_state":"Et doloribus ut ipsa et et aut.","texture_set_state":"Dolorem similique non reprehenderit."}}}},"tags":[{"name":"mktextr","description":"Texture store"}]}